magics/__init__.py
magics/client.py
magics/constants.py
magics/error.py
magics/filemanager.py
magics/magics_response.py
magics/version.py
magics/abstract/__init__.py
magics/abstract/api_requestor.py
magics/cli/__init__.py
magics/cli/cli.py
magics/cli/api/__init__.py
magics/cli/api/chat.py
magics/cli/api/completions.py
magics/cli/api/files.py
magics/cli/api/finetune.py
magics/cli/api/images.py
magics/cli/api/models.py
magics/cli/api/utils.py
magics/legacy/__init__.py
magics/legacy/base.py
magics/legacy/complete.py
magics/legacy/embeddings.py
magics/legacy/files.py
magics/legacy/finetune.py
magics/legacy/images.py
magics/legacy/models.py
magics/resources/__init__.py
magics/resources/completions.py
magics/resources/embeddings.py
magics/resources/files.py
magics/resources/finetune.py
magics/resources/gpus.py
magics/resources/images.py
magics/resources/models.py
magics/resources/rerank.py
magics/resources/resources.py
magics/resources/chat/__init__.py
magics/resources/chat/completions.py
magics/types/__init__.py
magics/types/abstract.py
magics/types/chat_completions.py
magics/types/common.py
magics/types/completions.py
magics/types/embeddings.py
magics/types/error.py
magics/types/files.py
magics/types/finetune.py
magics/types/images.py
magics/types/models.py
magics/types/rerank.py
magics/types/resources.py
magics/utils/__init__.py
magics/utils/_log.py
magics/utils/api_helpers.py
magics/utils/files.py
magics/utils/tools.py
magics_python-0.0.2.dist-info/LICENSE
magics_python-0.0.2.dist-info/METADATA
magics_python-0.0.2.dist-info/WHEEL
magics_python-0.0.2.dist-info/entry_points.txt
magics_python-0.0.2.dist-info/top_level.txt
magics_python-0.0.2.dist-info/RECORD
