Metadata-Version: 2.1
Name: magics-python
Version: 0.0.2
Summary: Python client for Magics's Cloud Platform!
Author: Magics AI
Author-email: support@magics.ai
License: Apache-2.0
Classifier: Programming Language :: Python :: 3
Classifier: License :: OSI Approved :: Apache Software License
Classifier: Operating System :: POSIX :: Linux
Requires-Python: >=3.8
License-File: LICENSE
Requires-Dist: typer<0.13,>=0.9
Requires-Dist: requests>=2.31.0
Requires-Dist: rich<14.0.0,>=13.8.1
Requires-Dist: tqdm>=4.66.2
Requires-Dist: tabulate>=0.9.0
Requires-Dist: pydantic>=2.6.3
Requires-Dist: aiohttp>=3.9.3
Requires-Dist: filelock>=3.13.1
Requires-Dist: eval-type-backport<0.3.0,>=0.1.3
Requires-Dist: click>=8.1.7
Requires-Dist: pillow>=10.3.0
Requires-Dist: pyarrow>=10.0.1
Requires-Dist: numpy>=1.23.5; python_version < "3.12"
Requires-Dist: numpy>=1.26.0; python_version >= "3.12"
